swjff/__init__.py
swjff/__init__.pyi
swjff/essentials/__init__.py
swjff/essentials/__init__.pyi
swjff/essentials/decoder.py
swjff/essentials/decoder.pyi
swjff/essentials/encoder.py
swjff/essentials/encoder.pyi
swjff/full/__init__.py
swjff/full/__init__.pyi
swjff/full/cryptography.py
swjff/full/file_manager.py
swjff/full/file_manager.pyi
SWJFF-1.0.0.0.dist-info/LICENSE
SWJFF-1.0.0.0.dist-info/METADATA
SWJFF-1.0.0.0.dist-info/WHEEL
SWJFF-1.0.0.0.dist-info/top_level.txt
SWJFF-1.0.0.0.dist-info/RECORD
