Metadata-Version: 2.1
Name: SWJFF
Version: 1.0.0.0
Summary: A module that serializes/deserializes data
Home-page: https://github.com/flamfrosticboio/SWJFF-Module-Python
Author: flamfrostboio
Classifier: Programming Language :: Python :: 3
Classifier: License :: OSI Approved :: Apache Software License
Classifier: Operating System :: OS Independent
Requires-Python: >=3.8
License-File: LICENSE
Requires-Dist: cryptography
Requires-Dist: zstandard
